pymrt/__init__.py
pymrt/_version.py
pymrt/animate.py
pymrt/batch.py
pymrt/computation.py
pymrt/config.py
pymrt/constants.py
pymrt/correction.py
pymrt/correlation.py
pymrt/input_output.py
pymrt/naming.py
pymrt/plot.py
pymrt/registration.py
pymrt/segmentation.py
pymrt/util.py
pymrt/extras/__init__.py
pymrt/extras/bruker.py
pymrt/extras/cfl.py
pymrt/extras/em_fields.py
pymrt/extras/html_ext.py
pymrt/extras/ismrmrd.py
pymrt/extras/jcampdx.py
pymrt/extras/latex.py
pymrt/extras/lcmodel.py
pymrt/extras/matlab.py
pymrt/extras/num_phantom.py
pymrt/extras/siemens.py
pymrt/recipes/__init__.py
pymrt/recipes/b1r.py
pymrt/recipes/b1t.py
pymrt/recipes/chi.py
pymrt/recipes/coils.py
pymrt/recipes/db0.py
pymrt/recipes/generic.py
pymrt/recipes/multi_echo.py
pymrt/recipes/multi_flash.py
pymrt/recipes/phs.py
pymrt/recipes/qmt.py
pymrt/recipes/quality.py
pymrt/recipes/reco.py
pymrt/recipes/rho.py
pymrt/recipes/t1.py
pymrt/recipes/t1r.py
pymrt/recipes/t2.py
pymrt/recipes/temperature.py
pymrt/resources/__init__.py
pymrt/sequences/__init__.py
pymrt/sequences/flash.py
pymrt/sequences/gradients.py
pymrt/sequences/matrix_algebra.py
pymrt/sequences/mp2rage.py
pymrt/sequences/rare.py
pymrt/sequences/trajectories.py
pymrt/sequences/pulses/GAUSS5120.csv
pymrt-0.0.3.5.data/data/share/icons/pymrt_logo.svg
scripts_cli/__init__.py
scripts_cli/batch_compute.py
scripts_cli/calc_mask.py
scripts_cli/coil_combine.py
scripts_cli/correlate.py
scripts_cli/ernst_calc.py
scripts_cli/extract_nifti_bruker.py
scripts_cli/filter.py
scripts_cli/gen_phantom.py
scripts_cli/unwrap.py
scripts_gui/__init__.py
scripts_gui/flash_ernst_angle.py
scripts_gui/fmri_te.py
scripts_gui/mp2rage_b1t_sensitivity_t1.py
scripts_gui/mp2rage_t1_sensitivity_b1t.py
scripts_gui/playgrounds.py
pymrt-0.0.3.5.dist-info/AUTHORS.rst
pymrt-0.0.3.5.dist-info/LICENSE.rst
pymrt-0.0.3.5.dist-info/METADATA
pymrt-0.0.3.5.dist-info/WHEEL
pymrt-0.0.3.5.dist-info/entry_points.txt
pymrt-0.0.3.5.dist-info/top_level.txt
pymrt-0.0.3.5.dist-info/RECORD
