Metadata-Version: 2.1
Name: pymrt
Version: 0.0.3.5
Summary: Python Magnetic Resonace Tools
Home-page: https://github.com/norok2/pymrt
Author: Riccardo Metere
Author-email: rick@metere.it
License: GPLv3+
Keywords: quantitative,MRI,qMRI,MT,susceptibility,relaxometry,qMT,neurophysics,neurology,physics,imaging,data,analysis
Platform: UNKNOWN
Classifier: Development Status :: 3 - Alpha
Classifier: Environment :: Console
Classifier: Environment :: X11 Applications
Classifier: Intended Audience :: Science/Research
Classifier: Intended Audience :: Healthcare Industry
Classifier: Intended Audience :: System Administrators
Classifier: Topic :: Scientific/Engineering
Classifier: Topic :: Scientific/Engineering :: Mathematics
Classifier: Topic :: Scientific/Engineering :: Physics
Classifier: Topic :: Scientific/Engineering :: Medical Science Apps.
Classifier: Topic :: Scientific/Engineering :: Information Analysis
Classifier: Topic :: Scientific/Engineering :: Visualization
Classifier: Topic :: Utilities
Classifier: Operating System :: POSIX
Classifier: Natural Language :: English
Classifier: License :: OSI Approved :: GNU General Public License v3 or later (GPLv3+)
Classifier: Programming Language :: Python
Classifier: Programming Language :: Python :: 3
Classifier: Programming Language :: Python :: 3.6
License-File: LICENSE.rst
License-File: AUTHORS.rst
Requires-Dist: appdirs
Requires-Dist: flyingcircus
Requires-Dist: flyingcircus-numeric
Requires-Dist: h5py
Requires-Dist: matplotlib
Requires-Dist: nibabel
Requires-Dist: numeral
Requires-Dist: numex
Requires-Dist: numpy
Requires-Dist: pillow
Requires-Dist: pyparsing
Requires-Dist: pytk
Requires-Dist: pywavelets
Requires-Dist: raster-geometry
Requires-Dist: scipy
Requires-Dist: seaborn
Requires-Dist: sympy
Provides-Extra: blessed
Requires-Dist: blessed ; extra == 'blessed'
Provides-Extra: skimage
Requires-Dist: scikit.image ; extra == 'skimage'
Provides-Extra: weasyprint
Requires-Dist: weasyprint ; extra == 'weasyprint'
